<?xml version="1.0" encoding="UTF-8"?>
<objects serializationModel="Studio.01.10.00">
    <object class="AudioFile" id="{764f37dc-3cea-48bb-92d6-3bc859094e81}">
        <property name="assetPath">
            <value>TD_Fix_FX_01.wav</value>
        </property>
        <property name="frequencyInKHz">
            <value>48</value>
        </property>
        <property name="channelCount">
            <value>1</value>
        </property>
        <property name="length">
            <value>0.087437500000000001</value>
        </property>
        <relationship name="masterAssetFolder">
            <destination>{d6a76e18-bc58-4c11-80e3-56c428795893}</destination>
        </relationship>
    </object>
</objects>
